{"msg":null,"success":true,"requestId":null,"resubmitToken":null,"content":{"pageNo":61,"pageSize":15,"positionResult":{"queryAnalysisInfo":{"industryName":null,"usefulCompany":false,"positionName":"php","companyName":null},"strategyProperty":{"name":"dm-csearch-newSimScorer","id":1},"totalCount":9416,"resultSize":15,"locationInfo":{"businessZone":null,"locationCode":null,"queryByGisCode":false,"city":"北京","district":null},"result":[{"companyId":55314,"explain":null,"plus":null,"pcShow":0,"appShow":0,"deliver":0,"gradeDescription":null,"businessZones":null,"imState":"today","lastLogin":1472561342000,"publisherId":1375680,"positionName":"PHP高级工程师/开发总监","workYear":"3-5年","education":"本科","jobNature":"全职","positionId":2279167,"createTime":"2016-08-23 21:56:37","city":"北京","companyLogo":"image1/M00/0E/20/Cgo8PFT5bmqAHd9zAAB4RxbLu9E280.png","industryField":"移动互联网,广告营销","positionAdvantage":"内部创业项目；期权制度激励；服务知名客户","salary":"25k-50k","companySize":"15-50人","approve":1,"financeStage":"成长型(A轮)","companyLabelList":["年底双薪","领导好","五险一金","午餐补助"],"district":null,"companyShortName":"海知见","score":0,"formatCreateTime":"2016-08-23","companyFullName":"海知见信息技术（北京）有限公司","adWord":0},{"companyId":114110,"explain":null,"plus":null,"pcShow":0,"appShow":0,"deliver":0,"gradeDescription":null,"businessZones":null,"imState":"disabled","lastLogin":1472199646000,"publisherId":926498,"positionName":"PHP高级开发工程师","workYear":"3-5年","education":"本科","jobNature":"全职","positionId":2021217,"createTime":"2016-08-23 20:58:22","city":"北京","companyLogo":"i/image/M00/04/2B/Cgp3O1bGwzWAEAB4AAAbnMQCudk783.jpg","industryField":"移动互联网","positionAdvantage":"各种补助、六险一金、补充医疗、年底多薪","salary":"15k-22k","companySize":"2000人以上","approve":1,"financeStage":"上市公司","companyLabelList":["股票期权","交通补助","通讯津贴","带薪年假"],"district":null,"companyShortName":"乐视","score":0,"formatCreateTime":"2016-08-23","companyFullName":"乐视网信息技术（北京）股份有限公司","adWord":0},{"companyId":13321,"explain":null,"plus":null,"pcShow":0,"appShow":0,"deliver":0,"gradeDescription":null,"businessZones":["中关村","知春路","双榆树"],"imState":"today","lastLogin":1472552889000,"publisherId":285309,"positionName":"高级PHP开发工程师","workYear":"3-5年","education":"本科","jobNature":"全职","positionId":2279101,"createTime":"2016-08-23 20:44:35","city":"北京","companyLogo":"image1/M00/00/1A/Cgo8PFTUWFWAKE5aAABwJ1mgAYw423.png","industryField":"游戏","positionAdvantage":"弹性工作、海外项目、靠谱团队、年假、奖金","salary":"20k-30k","companySize":"150-500人","approve":0,"financeStage":"成长型(B轮)","companyLabelList":["绩效奖金","股票期权","专项奖金","五险一金"],"district":"海淀区","companyShortName":"FunPlus 趣加游戏","score":0,"formatCreateTime":"2016-08-23","companyFullName":"北京趣加科技有限公司","adWord":0},{"companyId":113856,"explain":null,"plus":null,"pcShow":0,"appShow":0,"deliver":0,"gradeDescription":null,"businessZones":["上地","西二旗","马连洼"],"imState":"sevenDays","lastLogin":1472054016000,"publisherId":4768675,"positionName":"PHP","workYear":"1-3年","education":"本科","jobNature":"全职","positionId":1973879,"createTime":"2016-08-23 19:57:51","city":"北京","companyLogo":"i/image/M00/4E/40/CgqKkVeqlb2AF8JlAAAktQnnu8U850.png","industryField":"移动互联网,教育","positionAdvantage":"男女比例协调、技术氛围浓厚、免费三餐","salary":"15k-30k","companySize":"150-500人","approve":0,"financeStage":"成长型(B轮)","companyLabelList":["股票期权","免费三餐","打车报销","14薪"],"district":"海淀区","companyShortName":"作业帮","score":0,"formatCreateTime":"2016-08-23","companyFullName":"小船出海教育科技（北京）有限公司","adWord":0},{"companyId":134002,"explain":null,"plus":null,"pcShow":0,"appShow":0,"deliver":0,"gradeDescription":null,"businessZones":null,"imState":"today","lastLogin":1472545019000,"publisherId":5663270,"positionName":"PHP【北京试用 杭州上班】","workYear":"1-3年","education":"不限","jobNature":"全职","positionId":2212484,"createTime":"2016-08-23 19:42:39","city":"北京","companyLogo":"i/image/M00/36/3F/CgqKkVddLGWAK1HKAACPoL4rP0Q413.jpg","industryField":"电子商务,移动互联网","positionAdvantage":"氛围好 环境好 公司发展前景广阔 妹子多","salary":"9k-15k","companySize":"150-500人","approve":0,"financeStage":"成长型(A轮)","companyLabelList":null,"district":null,"companyShortName":"共创物联网","score":0,"formatCreateTime":"2016-08-23","companyFullName":"共创物联网科技（东莞）有限公司","adWord":0},{"companyId":114259,"explain":null,"plus":null,"pcShow":0,"appShow":0,"deliver":0,"gradeDescription":null,"businessZones":["上地","马连洼"],"imState":"sevenDays","lastLogin":1472193418000,"publisherId":5447711,"positionName":"PHP","workYear":"3-5年","education":"大专","jobNature":"全职","positionId":2006592,"createTime":"2016-08-23 19:10:39","city":"北京","companyLogo":"i/image/M00/03/9A/CgqKkVbBkYyAV_3AAAAYK2bvgTg524.png","industryField":"教育","positionAdvantage":"企业大，晋升空间大，不加班","salary":"15k-20k","companySize":"2000人以上","approve":1,"financeStage":"初创型(未融资)","companyLabelList":null,"district":"海淀区","companyShortName":"北京八维研修学院","score":0,"formatCreateTime":"2016-08-23","companyFullName":"北京八维研修学院","adWord":0},{"companyId":718,"explain":null,"plus":null,"pcShow":0,"appShow":0,"deliver":0,"gradeDescription":null,"businessZones":["知春路","中关村","双榆树"],"imState":"disabled","lastLogin":1472554505000,"publisherId":5813260,"positionName":"PHP","workYear":"3-5年","education":"本科","jobNature":"全职","positionId":2177277,"createTime":"2016-08-23 19:07:14","city":"北京","companyLogo":"image1/M00/10/F6/Cgo8PFT_8gyAHE_VAACEHkeY0jo769.jpg","industryField":"移动互联网","positionAdvantage":"广阔发展前景、竞争性福利、良好技术氛围","salary":"18k-30k","companySize":"2000人以上","approve":1,"financeStage":"上市公司","companyLabelList":["节日礼物","技能培训","免费娱乐设施","岗位晋升"],"district":"海淀区","companyShortName":"腾讯","score":0,"formatCreateTime":"2016-08-23","companyFullName":"腾讯科技(北京)有限公司","adWord":0},{"companyId":54952,"explain":null,"plus":null,"pcShow":0,"appShow":0,"deliver":0,"gradeDescription":null,"businessZones":["五道口","中关村","清华大学"],"imState":"today","lastLogin":1472545663000,"publisherId":1369044,"positionName":"PHP","workYear":"3-5年","education":"本科","jobNature":"全职","positionId":2116766,"createTime":"2016-08-23 18:56:17","city":"北京","companyLogo":"image1/M00/18/0E/Cgo8PFUTfiyAeu51AAB8LNm8hUI747.png","industryField":"移动互联网","positionAdvantage":"五险一金有期权，提供早餐午餐，水果零食等","salary":"15k-25k","companySize":"50-150人","approve":1,"financeStage":"成长型(A轮)","companyLabelList":["技能培训","节日礼物","绩效奖金","岗位晋升"],"district":"海淀区","companyShortName":"一家民宿","score":0,"formatCreateTime":"2016-08-23","companyFullName":"北京一游网络科技有限公司","adWord":0},{"companyId":25440,"explain":null,"plus":null,"pcShow":0,"appShow":0,"deliver":0,"gradeDescription":null,"businessZones":["西三旗","清河","小营"],"imState":"today","lastLogin":1472538088000,"publisherId":2437196,"positionName":"PHP开发工程师","workYear":"1-3年","education":"本科","jobNature":"全职","positionId":1996671,"createTime":"2016-08-23 18:56:02","city":"北京","companyLogo":"image1/M00/00/35/CgYXBlTUXJWAd5rjAACUoTxxHWg339.png","industryField":"移动互联网,广告营销","positionAdvantage":"14薪+餐补+试用期全薪+国外旅行+水果管够","salary":"10k-20k","companySize":"50-150人","approve":1,"financeStage":"成长型(A轮)","companyLabelList":["带薪年假","定期体检","水果零食","年终奖"],"district":"海淀区","companyShortName":"北京云图微动科技有限公司","score":0,"formatCreateTime":"2016-08-23","companyFullName":"北京云图微动科技有限公司","adWord":0},{"companyId":78820,"explain":null,"plus":null,"pcShow":0,"appShow":0,"deliver":0,"gradeDescription":null,"businessZones":["工体","朝阳门","三里屯"],"imState":"today","lastLogin":1472552049000,"publisherId":4243396,"positionName":"PHP","workYear":"1-3年","education":"本科","jobNature":"全职","positionId":1606555,"createTime":"2016-08-23 18:54:59","city":"北京","companyLogo":"image1/M00/34/3B/Cgo8PFWWTSqAdFL1AAASrmZFd0A559.jpg","industryField":"移动互联网,O2O","positionAdvantage":"创业公司平台好、潜力大、五险一金","salary":"15k-25k","companySize":"15-50人","approve":1,"financeStage":"初创型(天使轮)","companyLabelList":["年底双薪","股票期权","带薪年假","扁平管理"],"district":"东城区","companyShortName":"果皮移动","score":0,"formatCreateTime":"2016-08-23","companyFullName":"北京果皮移动科技有限公司","adWord":0},{"companyId":17851,"explain":null,"plus":null,"pcShow":0,"appShow":0,"deliver":0,"gradeDescription":null,"businessZones":["京广桥","朝外","东大桥"],"imState":"disabled","lastLogin":1472433241000,"publisherId":5361126,"positionName":"PHP","workYear":"3-5年","education":"大专","jobNature":"全职","positionId":2278774,"createTime":"2016-08-23 18:47:28","city":"北京","companyLogo":"i/image/M00/50/E1/Cgp3O1e1WB6AGCWzAABDVeMnbhM083.jpg","industryField":"文化娱乐,分类信息","positionAdvantage":"五险一金、带薪年假、餐补","salary":"8k-15k","companySize":"2000人以上","approve":1,"financeStage":"上市公司","companyLabelList":["专项奖金","五险一金","带薪年假","节日礼物"],"district":"朝阳区","companyShortName":"东易日盛","score":0,"formatCreateTime":"2016-08-23","companyFullName":"东易日盛家居装饰集团股份有限公司","adWord":0},{"companyId":36094,"explain":null,"plus":null,"pcShow":0,"appShow":0,"deliver":0,"gradeDescription":null,"businessZones":["回龙观","龙泽"],"imState":"today","lastLogin":1472549529000,"publisherId":607186,"positionName":"PHP工程师","workYear":"1-3年","education":"大专","jobNature":"全职","positionId":853634,"createTime":"2016-08-23 18:35:17","city":"北京","companyLogo":"image1/M00/24/32/Cgo8PFVLITKABGigAABsD_Je5qw259.png","industryField":"移动互联网","positionAdvantage":"五险一金 节假日福利 良好的发展前景","salary":"8k-15k","companySize":"15-50人","approve":0,"financeStage":"初创型(不需要融资)","companyLabelList":["技能培训","专项奖金","绩效奖金","岗位晋升"],"district":"昌平区","companyShortName":"恒盛昊悦","score":0,"formatCreateTime":"2016-08-23","companyFullName":"北京恒盛昊悦科技有限责任公司","adWord":0},{"companyId":113883,"explain":null,"plus":null,"pcShow":0,"appShow":0,"deliver":0,"gradeDescription":null,"businessZones":["四季青"],"imState":"today","lastLogin":1472570194000,"publisherId":3795988,"positionName":"PHP","workYear":"不限","education":"不限","jobNature":"全职","positionId":1466702,"createTime":"2016-08-23 18:30:16","city":"北京","companyLogo":"i/image/M00/03/B6/CgqKkVbCxCCAGyGLAAAqUBza6v0643.png","industryField":"数据服务,金融","positionAdvantage":"弹性工作，风口行业","salary":"8k-16k","companySize":"15-50人","approve":0,"financeStage":"初创型(不需要融资)","companyLabelList":["带薪年假","专项奖金","年终分红","弹性工作"],"district":"海淀区","companyShortName":"发现征信","score":0,"formatCreateTime":"2016-08-23","companyFullName":"发现(北京)征信有限公司","adWord":0},{"companyId":81888,"explain":null,"plus":null,"pcShow":0,"appShow":0,"deliver":0,"gradeDescription":null,"businessZones":["中关村","知春路","双榆树"],"imState":"today","lastLogin":1472553989000,"publisherId":1931908,"positionName":"高级PHP开发工程师","workYear":"5-10年","education":"本科","jobNature":"全职","positionId":1372989,"createTime":"2016-08-23 18:16:11","city":"北京","companyLogo":"i/image/M00/03/B9/CgqKkVbC0_CACWDfAAAncHx33iw104.png","industryField":"移动互联网,教育","positionAdvantage":"优秀技术团队，晋升空间大，能力决定薪资。","salary":"20k-30k","companySize":"150-500人","approve":0,"financeStage":"成熟型(C轮)","companyLabelList":["节日礼物","年底双薪","带薪年假","岗位晋升"],"district":"海淀区","companyShortName":"51CTO传媒","score":0,"formatCreateTime":"2016-08-23","companyFullName":"北京无忧创想信息技术有限公司","adWord":0},{"companyId":56417,"explain":null,"plus":null,"pcShow":0,"appShow":0,"deliver":0,"gradeDescription":null,"businessZones":["亮马桥","三元桥","燕莎"],"imState":"disabled","lastLogin":1471946981000,"publisherId":2790359,"positionName":"PHP软件开发工程师","workYear":"3-5年","education":"大专","jobNature":"全职","positionId":1637631,"createTime":"2016-08-23 18:14:56","city":"北京","companyLogo":"image1/M00/10/F2/Cgo8PFT_7NCACofHAAA7v9zPr8s477.jpg","industryField":"移动互联网,社交网络","positionAdvantage":"聘有经验开发工程师","salary":"15k-25k","companySize":"15-50人","approve":1,"financeStage":"初创型(天使轮)","companyLabelList":["技能培训","股票期权","专项奖金","绩效奖金"],"district":"朝阳区","companyShortName":"四普海威","score":0,"formatCreateTime":"2016-08-23","companyFullName":"北京硕邦伟业科技发展有限公司","adWord":0}]}},"code":0}