{"success":true,"requestId":null,"msg":null,"resubmitToken":null,"content":{"pageNo":69,"pageSize":15,"positionResult":{"totalCount":9416,"resultSize":15,"locationInfo":{"city":"北京","district":null,"queryByGisCode":false,"businessZone":null,"locationCode":null},"queryAnalysisInfo":{"positionName":"php","companyName":null,"usefulCompany":false,"industryName":null},"strategyProperty":{"name":"dm-csearch-newSimScorer","id":1},"result":[{"companyId":111175,"companyShortName":"智线云科技","createTime":"2016-08-23 11:38:10","positionId":1930545,"positionAdvantage":"带薪年假+福利多+办公环境好+氛围自由开放","salary":"10k-18k","score":0,"workYear":"1-3年","education":"不限","city":"北京","positionName":"PHP 中级工程师","companyLogo":"i/image/M00/34/9D/CgqKkVdWPSeAK6YCAAIELNuwlYo561.png","financeStage":"初创型(天使轮)","industryField":"移动互联网,广告营销","jobNature":"全职","approve":0,"companySize":"15-50人","district":null,"companyLabelList":["绩效奖金","股票期权","带薪年假","弹性工作"],"adWord":0,"appShow":0,"deliver":0,"formatCreateTime":"2016-08-23","gradeDescription":null,"companyFullName":"智线云科技（北京）有限公司","businessZones":null,"imState":"today","lastLogin":1472561210000,"publisherId":3626897,"explain":null,"plus":null,"pcShow":0},{"companyId":36513,"companyShortName":"微创","createTime":"2016-08-23 10:57:23","positionId":2274785,"positionAdvantage":"六险一金 带薪年假 带薪病假 百度办公","salary":"10k-15k","score":0,"workYear":"3-5年","education":"大专","city":"北京","positionName":"高级PHP工程师","companyLogo":"i/image/M00/01/B2/Cgp3O1Zzr9GAdpGkAAAWW2BuXJc040.png","financeStage":"成熟型(不需要融资)","industryField":"移动互联网,电子商务","jobNature":"全职","approve":0,"companySize":"2000人以上","district":"海淀区","companyLabelList":["年底双薪","节日礼物","技能培训","免费班车"],"adWord":0,"appShow":0,"deliver":0,"formatCreateTime":"2016-08-23","gradeDescription":null,"companyFullName":"上海微创软件股份有限公司北京分公司","businessZones":null,"imState":"disabled","lastLogin":1472548267000,"publisherId":3435204,"explain":null,"plus":null,"pcShow":0},{"companyId":122231,"companyShortName":"泰岳教育","createTime":"2016-08-23 10:45:24","positionId":2009631,"positionAdvantage":"专注“互联网+”创新创业人才培养。","salary":"10k-15k","score":0,"workYear":"3-5年","education":"大专","city":"北京","positionName":"PHP开发工程师","companyLogo":"i/image/M00/1A/8B/CgqKkVb6TNCADCwLAAAd6FZyVwo930.png","financeStage":"成长型(不需要融资)","industryField":"教育","jobNature":"全职","approve":1,"companySize":"50-150人","district":"朝阳区","companyLabelList":["年终分红","绩效奖金","带薪年假","午餐补助"],"adWord":0,"appShow":0,"deliver":0,"formatCreateTime":"2016-08-23","gradeDescription":null,"companyFullName":"北京神州泰岳教育科技有限公司","businessZones":["北苑","立水桥"],"imState":"today","lastLogin":1472539235000,"publisherId":4676079,"explain":null,"plus":null,"pcShow":0},{"companyId":41030,"companyShortName":"小肚皮App","createTime":"2016-08-23 10:32:56","positionId":1606899,"positionAdvantage":"逗逼氛围、五险一金、年度旅游、餐补、房补","salary":"10k-20k","score":0,"workYear":"不限","education":"本科","city":"北京","positionName":"PHP","companyLogo":"i/image/M00/1C/42/Cgp3O1cA5FCAAbd-AADMvrUkPw8952.png","financeStage":"成长型(A轮)","industryField":"移动互联网","jobNature":"全职","approve":1,"companySize":"15-50人","district":"朝阳区","companyLabelList":["年度旅游","美女CEO","五险一金","午餐补助"],"adWord":0,"appShow":0,"deliver":0,"formatCreateTime":"2016-08-23","gradeDescription":null,"companyFullName":"北京九识佳科技有限公司","businessZones":["大望路","红庙","华贸"],"imState":"sevenDays","lastLogin":1472140598000,"publisherId":795835,"explain":null,"plus":null,"pcShow":0},{"companyId":41731,"companyShortName":"云智汇","createTime":"2016-08-23 10:07:41","positionId":1615605,"positionAdvantage":"招募核心主力，股权激励","salary":"15k-25k","score":0,"workYear":"3-5年","education":"大专","city":"北京","positionName":"PHP","companyLogo":"images/logo_default.png","financeStage":"初创型(未融资)","industryField":"移动互联网,教育","jobNature":"全职","approve":0,"companySize":"15-50人","district":"朝阳区","companyLabelList":["技能培训","节日礼物","股票期权","带薪年假"],"adWord":0,"appShow":0,"deliver":0,"formatCreateTime":"2016-08-23","gradeDescription":null,"companyFullName":"北京云智汇科技有限公司","businessZones":["双井","南磨房","劲松"],"imState":"disabled","lastLogin":1472436186000,"publisherId":846455,"explain":null,"plus":null,"pcShow":0},{"companyId":99100,"companyShortName":"百程旅行网","createTime":"2016-08-23 10:06:44","positionId":2274107,"positionAdvantage":"海外旅游奖励，五险一金，上市公司","salary":"15k-20k","score":0,"workYear":"3-5年","education":"本科","city":"北京","positionName":"PHP开发","companyLogo":"image2/M00/0A/78/CgpzWlYV1pyAdVmpAABg8IADQ_k955.png?cc=0.1954620119649917","financeStage":"上市公司","industryField":"O2O,旅游","jobNature":"全职","approve":1,"companySize":"500-2000人","district":"朝阳区","companyLabelList":["节日礼物","免费班车","股票期权","带薪年假"],"adWord":0,"appShow":0,"deliver":0,"formatCreateTime":"2016-08-23","gradeDescription":null,"companyFullName":"北京百程国际旅游有限公司","businessZones":["高碑店","四惠","十里堡"],"imState":"disabled","lastLogin":1472455259000,"publisherId":4510066,"explain":null,"plus":null,"pcShow":0},{"companyId":50341,"companyShortName":"活动树","createTime":"2016-08-23 10:00:41","positionId":1785033,"positionAdvantage":"有前景的O2O，弹性工作，美女如云","salary":"15k-30k","score":0,"workYear":"5-10年","education":"本科","city":"北京","positionName":"PHP架构师","companyLogo":"image1/M00/00/84/CgYXBlTUXeKAdRMlAABBaDEeZiE728.png","financeStage":"上市公司","industryField":"移动互联网,O2O","jobNature":"全职","approve":1,"companySize":"50-150人","district":"朝阳区","companyLabelList":["节日礼物","免费班车","带薪年假","扁平管理"],"adWord":0,"appShow":0,"deliver":0,"formatCreateTime":"2016-08-23","gradeDescription":null,"companyFullName":"活动树（北京）科技有限公司","businessZones":["大山子","酒仙桥"],"imState":"disabled","lastLogin":1471931949000,"publisherId":1305250,"explain":null,"plus":null,"pcShow":0},{"companyId":86456,"companyShortName":"Baca","createTime":"2016-08-23 10:00:17","positionId":2136483,"positionAdvantage":"待遇优厚；晋升/发展空间大；","salary":"15k-25k","score":0,"workYear":"不限","education":"本科","city":"北京","positionName":"PHP开发","companyLogo":"i/image/M00/0F/CF/CgqKkVbejOiAKV3dAAB-iAxLQIw843.jpg","financeStage":"成长型(A轮)","industryField":"移动互联网","jobNature":"全职","approve":0,"companySize":"15-50人","district":"海淀区","companyLabelList":["技能培训","股票期权","带薪年假","绩效奖金"],"adWord":0,"appShow":0,"deliver":0,"formatCreateTime":"2016-08-23","gradeDescription":null,"companyFullName":"五洲万象（北京）科技有限公司","businessZones":["北京大学","苏州街"],"imState":"today","lastLogin":1472552256000,"publisherId":2210271,"explain":null,"plus":null,"pcShow":0},{"companyId":2768,"companyShortName":"易到用车","createTime":"2016-08-23 09:56:50","positionId":2058636,"positionAdvantage":"六险一金,绩效奖金,专业团队,舒适环境","salary":"14k-20k","score":0,"workYear":"3-5年","education":"本科","city":"北京","positionName":"PHP","companyLogo":"i/image/M00/47/3B/CgqKkVeO8sWAS9d9AAAgP9GL_Zc630.png","financeStage":"成熟型(C轮)","industryField":"移动互联网,O2O","jobNature":"全职","approve":1,"companySize":"500-2000人","district":"海淀区","companyLabelList":["节日礼物","绩效奖金","岗位晋升","年度旅游"],"adWord":0,"appShow":0,"deliver":0,"formatCreateTime":"2016-08-23","gradeDescription":null,"companyFullName":"北京东方车云信息技术有限公司","businessZones":["苏州街","北京大学","颐和园"],"imState":"disabled","lastLogin":1472557230000,"publisherId":4666534,"explain":null,"plus":null,"pcShow":0},{"companyId":83608,"companyShortName":"智博联才","createTime":"2016-08-23 09:48:01","positionId":2273847,"positionAdvantage":"互联网+新能源 稳定性好 垄断行业","salary":"18k-30k","score":0,"workYear":"3-5年","education":"本科","city":"北京","positionName":"PHP","companyLogo":"image1/M00/39/99/CgYXBlWqEdOASshZAAAICQLcIH4085.jpg?cc=0.27826874097809196","financeStage":"成长型(A轮)","industryField":"移动互联网,招聘","jobNature":"全职","approve":0,"companySize":"50-150人","district":"海淀区","companyLabelList":["技能培训","年底双薪","股票期权","专项奖金"],"adWord":0,"appShow":0,"deliver":0,"formatCreateTime":"2016-08-23","gradeDescription":null,"companyFullName":"北京智博联才企业管理咨询有限公司","businessZones":null,"imState":"disabled","lastLogin":1472089588000,"publisherId":2136190,"explain":null,"plus":null,"pcShow":0},{"companyId":23507,"companyShortName":"国创科视","createTime":"2016-08-23 09:47:23","positionId":970545,"positionAdvantage":"七险一金 13薪 各种补助 北京居住证","salary":"10k-20k","score":0,"workYear":"1-3年","education":"大专","city":"北京","positionName":"PHP","companyLogo":"image1/M00/00/2E/CgYXBlTUXHyAeYpqAACK2WDLUL8290.png","financeStage":"成长型(A轮)","industryField":"移动互联网,数据服务","jobNature":"全职","approve":1,"companySize":"50-150人","district":"东城区","companyLabelList":["北京人才引进","岗位晋升","定期体检","通讯津贴"],"adWord":0,"appShow":0,"deliver":0,"formatCreateTime":"2016-08-23","gradeDescription":null,"companyFullName":"国创科视科技股份有限公司","businessZones":["安贞","安华","安定门"],"imState":"threeDays","lastLogin":1472434853000,"publisherId":1510787,"explain":null,"plus":null,"pcShow":0},{"companyId":77871,"companyShortName":"铁力山（北京）控制技术有限公司","createTime":"2016-08-23 09:46:56","positionId":804222,"positionAdvantage":"占据国内市场50%市场份额","salary":"20k-30k","score":0,"workYear":"3-5年","education":"本科","city":"北京","positionName":"PHP","companyLogo":"i/image/M00/00/95/Cgp3O1ZOhiOAMtd1AAAhMtlDptc620.gif","financeStage":"成熟型(C轮)","industryField":"移动互联网","jobNature":"全职","approve":0,"companySize":"150-500人","district":"朝阳区","companyLabelList":["年底双薪","带薪年假","帅哥多","通讯津贴"],"adWord":0,"appShow":0,"deliver":0,"formatCreateTime":"2016-08-23","gradeDescription":null,"companyFullName":"铁力山(北京)控制技术有限公司","businessZones":["望京","大山子","花家地"],"imState":"disabled","lastLogin":1472470482000,"publisherId":1958609,"explain":null,"plus":null,"pcShow":0},{"companyId":92282,"companyShortName":"国商易购","createTime":"2016-08-23 09:36:25","positionId":2273653,"positionAdvantage":"五险一金 年底双薪","salary":"10k-15k","score":0,"workYear":"3-5年","education":"本科","city":"北京","positionName":"PHP","companyLogo":"image2/M00/00/32/CgpzWlXdWg-ABFOwAAKgWXZV4f4955.png?cc=0.874275719281286","financeStage":"初创型(未融资)","industryField":"电子商务","jobNature":"全职","approve":0,"companySize":"15-50人","district":"丰台区","companyLabelList":["技能培训","年底双薪","带薪年假","绩效奖金"],"adWord":0,"appShow":0,"deliver":0,"formatCreateTime":"2016-08-23","gradeDescription":null,"companyFullName":"国商易购（北京）电子商务有限公司","businessZones":["东铁匠营","方庄","成寿寺"],"imState":"today","lastLogin":1472549946000,"publisherId":5129111,"explain":null,"plus":null,"pcShow":0},{"companyId":118038,"companyShortName":"北京晟德丰机电工程有限公司","createTime":"2016-08-23 09:36:09","positionId":1582113,"positionAdvantage":"双休、带薪年假","salary":"10k-20k","score":0,"workYear":"不限","education":"不限","city":"北京","positionName":"php程序员","companyLogo":"i/image/M00/11/86/Cgp3O1biOeOACYe0AAAcoKrdZ5Y455.jpg","financeStage":"成长型(不需要融资)","industryField":"移动互联网","jobNature":"全职","approve":0,"companySize":"50-150人","district":"朝阳区","companyLabelList":null,"adWord":0,"appShow":0,"deliver":0,"formatCreateTime":"2016-08-23","gradeDescription":null,"companyFullName":"北京晟德丰机电工程有限公司","businessZones":["CBD","双井","国贸"],"imState":"disabled","lastLogin":1471916085000,"publisherId":4366771,"explain":null,"plus":null,"pcShow":0},{"companyId":64229,"companyShortName":"中科同向","createTime":"2016-08-23 09:31:04","positionId":1486181,"positionAdvantage":"包住+餐补+五险一金","salary":"10k-20k","score":0,"workYear":"3-5年","education":"本科","city":"北京","positionName":"PHP开发工程师","companyLogo":"images/logo_default.png","financeStage":"初创型(天使轮)","industryField":"移动互联网,数据服务","jobNature":"全职","approve":0,"companySize":"50-150人","district":"海淀区","companyLabelList":["技能培训","股票期权","带薪年假","绩效奖金"],"adWord":0,"appShow":0,"deliver":0,"formatCreateTime":"2016-08-23","gradeDescription":null,"companyFullName":"北京中科同向信息技术有限公司","businessZones":["知春路","蓟门桥","学院路"],"imState":"disabled","lastLogin":1472539402000,"publisherId":1596239,"explain":null,"plus":null,"pcShow":0}]}},"code":0}